aiv/__init__.py
aiv/aivapp.py
aiv/aivlog.py
aiv/aivmmap.py
aiv/aivship.py
aiv/aivtool.py
aiv/aivvideo.py
aivm-0.1.2.dist-info/METADATA
aivm-0.1.2.dist-info/WHEEL
aivm-0.1.2.dist-info/top_level.txt
aivm-0.1.2.dist-info/RECORD
