Metadata-Version: 2.1
Name: aivm
Version: 0.1.2
Summary: AIV Manager
Home-page: https://www.aiv.store
Author: quicksoft
Author-email: 990420119@qq.com
License: MIT
Keywords: AIV Manager
